Topsis_Sarisha_102003445/Sarisha_102003445.py
Topsis_Sarisha_102003445-0.7.dist-info/METADATA
Topsis_Sarisha_102003445-0.7.dist-info/WHEEL
Topsis_Sarisha_102003445-0.7.dist-info/entry_points.txt
Topsis_Sarisha_102003445-0.7.dist-info/top_level.txt
Topsis_Sarisha_102003445-0.7.dist-info/RECORD
