Metadata-Version: 2.1
Name: Topsis-Sarisha-102003445
Version: 0.7
Summary: This is a topsis package of version 0.7
Author: Aditya Singh Rathore
Author-email: saggarwal4_be20@thapar.edu
License: UNKNOWN
Platform: UNKNOWN
Requires-Dist: pandas
